gitconnect/GitWrapper.py
gitconnect/__init__.py
gitconnect-0.1.5.dist-info/METADATA
gitconnect-0.1.5.dist-info/WHEEL
gitconnect-0.1.5.dist-info/top_level.txt
gitconnect-0.1.5.dist-info/RECORD
